phys_const/__init__.py
phys_const_pkg/__init__.py
phys_const-0.1.5.dist-info/LICENSE
phys_const-0.1.5.dist-info/METADATA
phys_const-0.1.5.dist-info/WHEEL
phys_const-0.1.5.dist-info/top_level.txt
phys_const-0.1.5.dist-info/RECORD
