Metadata-Version: 2.1
Name: phys-const
Version: 0.1.5
Summary: Pack of physical constants.
Home-page: https://github.com/Rezenter/phys-const
Author: Rezenter
Author-email: nisovru@gmail.com
License: UNKNOWN
Platform: UNKNOWN
Classifier: Programming Language :: Python :: 3
Classifier: License :: OSI Approved :: MIT License
Classifier: Operating System :: OS Independent
Requires-Python: >=3.6
License-File: LICENSE
